{
  "id": "std_da_retail_v1",
  "status": "active",
  "name": "Data Analyst (Retail)",
  "version": "v1.0",
  "division": "Analytics / Retail",
  "goal": "Давать управленческие инсайты для роста продажи/маржи: отчёты, модели, эксперименты.",
  "responsibilities": [
    "Сбор/очистка данных sell-in/sell-out/остатки/промо",
    "Дашборды и отчётность для KAM/RM/категорийщиков",
    "Аналитика промо и ценовой чувствительности",
    "Эксперименты и A/B, дизайн и оценка эффектов",
    "Прогнозирование спроса, сезонность, тренды",
    "Сегментация ассортимента и клиентов",
    "Data governance: качество, словарь, доступы",
    "Обучение пользователей работе с отчётами"
  ],
  "kpi": {
    "current": [
      { "name": "Доступность дашбордов", "target": "≥99%", "period": "месяц" },
      { "name": "Time-to-Insight", "target": "−20% QoQ", "period": "квартал" }
    ],
    "recommended": [
      { "name": "Точность прогноза", "target": "≥85%", "period": "месяц" },
      { "name": "Утилизация отчётов", "target": "≥80% активных пользователей", "period": "квартал" }
    ]
  },
  "competencyMap": {
    "Стратегическое мышление": 2,
    "Переговоры": 2,
    "Аналитика": 4,
    "Коммуникация": 4,
    "Лидерство": 2,
    "Финансовое мышление": 3,
    "Тайм-менеджмент": 3,
    "Проектное управление": 3
  },
  "assessmentGuidelines": {
    "scales": "Шкала 1–4; 4 — аналитика, приводящая к принятым решениям.",
    "behavioralAnchors": {
      "Аналитика": [
        "Готовит чистые датасеты и воспроизводимые расчёты",
        "Покрывает неопределённость: интервалы, чувствительность"
      ],
      "Коммуникация": [
        "Пишет понятные выводы и рекомендации non-tech аудитории",
        "Строит дашборды без визуального мусора"
      ]
    },
    "evidenceExamples": [
      "Снижение промо-утечек на 12% за счёт анализа",
      "Модель прогноза улучшила точность до 88%"
    ]
  },
  "testAssignment": {
    "objective": "Разобрать промо-эффективность и дать 3 управленческих инсайта.",
    "deliverables": [
      "Ноутбук/отчёт с расчётами",
      "Краткая записка с рекомендациями",
      "Дашборд (макет) для регулярного мониторинга"
    ],
    "evaluationCriteria": [
      "Качество данных/воспроизводимость",
      "Сила выводов и их польза",
      "Ясность визуализаций"
    ],
    "timeboxHours": 6
  },
  "assessmentCenter": {
    "cases": [
      {
        "title": "Падение sell-out при росте промо",
        "durationMin": 35,
        "observersRoles": ["Head of Analytics", "Sales Director"],
        "competenciesObserved": ["Аналитика", "Коммуникация", "Финансовое мышление"]
      }
    ],
    "rubrics": "Analytics Scorecard: Data → Model → Insight → Action"
  },
  "tags": ["analytics", "retail", "dashboards"],
  "meta": {},
  "createdAt": "2025-08-21",
  "updatedAt": "2025-08-21"
}
