{
  "id": "std_salesops_head_v1",
  "status": "active",
  "name": "Head of Sales Operations",
  "version": "v1.0",
  "division": "Sales / Operations",
  "goal": "Поднять управляемость продаж: планирование, процессы, инструменты, данные, скорость принятия решений.",
  "responsibilities": [
    "S&OP и ритм управления (каденция, дашборды, ретро)",
    "CRM/BI ландшафт: требования, внедрения, качество данных",
    "Пайплайн инициатив и их приоритизация",
    "Регламенты и стандарты полевого исполнения",
    "Коммерческий календарь: промо/выкладки/листинги",
    "Обучение продаж и методологическая поддержка",
    "Совместная работа с Finance/Logistics по SLA",
    "Контроль compliance по коммерческим процессам"
  ],
  "kpi": {
    "current": [
      { "name": "Принятие решений по каденции", "target": "100% еженедельных циклов", "period": "квартал" },
      { "name": "Доля чистых данных в CRM", "target": "≥95%", "period": "месяц" }
    ],
    "recommended": [
      { "name": "Cycle Time сделки/инициативы", "target": "−15% QoQ", "period": "квартал" },
      { "name": "Adoption новых инструментов", "target": "≥85%", "period": "квартал" }
    ]
  },
  "competencyMap": {
    "Стратегическое мышление": 3,
    "Переговоры": 3,
    "Аналитика": 4,
    "Коммуникация": 4,
    "Лидерство": 4,
    "Финансовое мышление": 3,
    "Тайм-менеджмент": 4,
    "Проектное управление": 4
  },
  "assessmentGuidelines": {
    "scales": "Шкала 1–4; 4 — процессная система, ускоряющая продажи.",
    "behavioralAnchors": {
      "Проектное управление": [
        "Ставит систему OKR/каденции, зашивает контроль качества",
        "Ведёт портфель инициатив и снимает блокеры"
      ],
      "Аналитика": [
        "Формирует единые метрики и дашборды",
        "Поддерживает единый словарь данных"
      ]
    },
    "evidenceExamples": [
      "Внедрена CRM-каденция, загрузка данных 98%",
      "Cycle Time укорочен на 22%"
    ]
  },
  "testAssignment": {
    "objective": "Собрать план Sales Ops трансформации на квартал.",
    "deliverables": [
      "Roadmap + метрики",
      "Схема данных/дашборд",
      "План внедрения и риски"
    ],
    "evaluationCriteria": [
      "Управляемость и измеримость",
      "Реалистичность сроков",
      "Управление изменениями"
    ],
    "timeboxHours": 6
  },
  "assessmentCenter": {
    "cases": [
      {
        "title": "Хаос в данных и срыв отчетности",
        "durationMin": 40,
        "observersRoles": ["Sales Director", "CIO"],
        "competenciesObserved": ["Проектное управление", "Аналитика", "Коммуникация"]
      }
    ],
    "rubrics": "Процессная матрица: People × Data × Tools × Cadence"
  },
  "tags": ["sales-ops", "process", "crm"],
  "meta": {},
  "createdAt": "2025-08-21",
  "updatedAt": "2025-08-21"
}
